{"Title": "Quarterly Results: {Company} Exceeds Expectations with Strong Performance", "Summary": "Despite exceeding expectations in its quarterly results, the company faces regulatory challenges and mixed investor sentiment. Strategic initiatives and expansion into new markets are underway to boost revenue and drive future growth.", "Sentiment": "Positive", "Sentiment_Score": 4, "Topics": ["Quarterly Results", "Strategic Initiatives", "Market Expansion", "Regulatory Challenges"], "Sentiment_Indicators": ["Exceeds Expectations", "Strong Performance", "New strategic initiatives to boost revenue", "Expanding into new markets to diversify revenue streams", "New product launches are expected to drive future growth", "Investors remain cautious about the company's growth prospects", "Regulatory challenges could impact the company's operations", "Market analysts have mixed opinions"]}